{
  "aor": 0.0007242207792207793,
  "aqi": 0.006935317987012987,
  "bids_meta": {
    "RepetitionTime": 2.0,
    "TaskName": "face identity oddball",
    "dataset": "ds001297",
    "modality": "bold",
    "run_id": 8,
    "subject_id": "13",
    "task_id": "faceidentityoddball"
  },
  "dummy_trs": 0,
  "dvars_nstd": 23.978478637320254,
  "dvars_std": 1.2101947160130722,
  "dvars_vstd": 1.0137408500653595,
  "efc": 0.448148913591336,
  "fber": 894170.9375,
  "fd_mean": 0.12241052353080085,
  "fd_num": 23,
  "fd_perc": 14.935064935064934,
  "fwhm_avg": 1.8393977777777775,
  "fwhm_x": 1.7438799999999999,
  "fwhm_y": 2.08626,
  "fwhm_z": 1.6880533333333334,
  "gcor": 0.0805916,
  "gsr_x": -0.014035457745194435,
  "gsr_y": 0.012934689410030842,
  "provenance": {
    "md5sum": "efc97ad0c3b172614f418705f35cd14e",
    "settings": {
      "fd_thres": 0.2,
      "testing": false
    },
    "software": "mriqc",
    "version": "22.0.6",
    "webapi_port": null,
    "webapi_url": "https://mriqc.nimh.nih.gov/api/v1"
  },
  "size_t": 154,
  "size_x": 80,
  "size_y": 80,
  "size_z": 35,
  "snr": 5.972444110695373,
  "spacing_tr": 2.0,
  "spacing_x": 3.0,
  "spacing_y": 3.0,
  "spacing_z": 3.0,
  "summary_bg_k": 132.06425572017534,
  "summary_bg_mad": 1.5837447805876987,
  "summary_bg_mean": 19.203807830810547,
  "summary_bg_median": 1.071350336074829,
  "summary_bg_n": 145441.0,
  "summary_bg_p05": 0.0026450851000845432,
  "summary_bg_p95": 90.22478485107422,
  "summary_bg_stdv": 61.837154388427734,
  "summary_fg_k": 2.5159269749042013,
  "summary_fg_mad": 150.16690947537845,
  "summary_fg_mean": 979.85205078125,
  "summary_fg_median": 972.2063598632812,
  "summary_fg_n": 38446.0,
  "summary_fg_p05": 739.7776641845703,
  "summary_fg_p95": 1233.8315124511719,
  "summary_fg_stdv": 162.77987670898438,
  "tsnr": 67.48131561279297
}